<?xml version="1.0" encoding="utf-8" ?>
<odoo>
    <!-- Employee View -->
    <record id="hr_employee_view_form" model="ir.ui.view">
        <field name="name">hr.employee.experiece.view.form</field>
        <field name="model">hr.employee</field>
        <field name="inherit_id" ref="hr.view_employee_form" />
        <field name="arch" type="xml">
            <xpath expr="//field[@name='country_of_birth']" position="after">
                <field name="birth_state_id" />
                <field name="ethnicity_id" />
                <field name="religion_id" />
                <field name="blood_type" />
                <field name="blood_type_rhesus" />
            </xpath>
        </field>
    </record>
</odoo>
